rootmd/Executor.py
rootmd/Md2MacroRenderer.py
rootmd/RootBaseRenderer.py
rootmd/RootHtmlRenderer.py
rootmd/RootMdRenderer.py
rootmd/YamlBlock.py
rootmd/__init__.py
rootmd/__main__.py
rootmd/data/css/core.css
rootmd/data/css/prismjs/prism-a11y-dark.css
rootmd/data/css/prismjs/prism-atom-dark.css
rootmd/data/css/prismjs/prism-base16-ateliersulphurpool.light.css
rootmd/data/css/prismjs/prism-cb.css
rootmd/data/css/prismjs/prism-coldark-cold.css
rootmd/data/css/prismjs/prism-coldark-dark.css
rootmd/data/css/prismjs/prism-coy-without-shadows.css
rootmd/data/css/prismjs/prism-coy.css
rootmd/data/css/prismjs/prism-coy.min.css
rootmd/data/css/prismjs/prism-darcula.css
rootmd/data/css/prismjs/prism-dark.css
rootmd/data/css/prismjs/prism-dark.min.css
rootmd/data/css/prismjs/prism-dracula.css
rootmd/data/css/prismjs/prism-duotone-dark.css
rootmd/data/css/prismjs/prism-duotone-earth.css
rootmd/data/css/prismjs/prism-duotone-forest.css
rootmd/data/css/prismjs/prism-duotone-light.css
rootmd/data/css/prismjs/prism-duotone-sea.css
rootmd/data/css/prismjs/prism-duotone-space.css
rootmd/data/css/prismjs/prism-funky.css
rootmd/data/css/prismjs/prism-funky.min.css
rootmd/data/css/prismjs/prism-ghcolors.css
rootmd/data/css/prismjs/prism-gruvbox-dark.css
rootmd/data/css/prismjs/prism-gruvbox-light.css
rootmd/data/css/prismjs/prism-holi-theme.css
rootmd/data/css/prismjs/prism-hopscotch.css
rootmd/data/css/prismjs/prism-lucario.css
rootmd/data/css/prismjs/prism-material-dark.css
rootmd/data/css/prismjs/prism-material-light.css
rootmd/data/css/prismjs/prism-material-oceanic.css
rootmd/data/css/prismjs/prism-night-owl.css
rootmd/data/css/prismjs/prism-nord.css
rootmd/data/css/prismjs/prism-okaidia.css
rootmd/data/css/prismjs/prism-okaidia.min.css
rootmd/data/css/prismjs/prism-one-dark.css
rootmd/data/css/prismjs/prism-one-light.css
rootmd/data/css/prismjs/prism-pojoaque.css
rootmd/data/css/prismjs/prism-shades-of-purple.css
rootmd/data/css/prismjs/prism-solarized-dark-atom.css
rootmd-0.6.1.dist-info/LICENSE
rootmd-0.6.1.dist-info/METADATA
rootmd-0.6.1.dist-info/WHEEL
rootmd-0.6.1.dist-info/RECORD
